templatemail/__init__.py
templatemail/engines/__init__.py
templatemail/engines/mailgun.py
templatemail/engines/smtp.py
templatemail/templates/_render_html_body.html
templatemail/templates/_render_subject.html
templatemail/templates/_render_text_body.html
templatemail/templates/base.html
templatemail/templates/mailgun-transactional/action.html
templatemail/templates/mailgun-transactional/alert.html
templatemail/templates/mailgun-transactional/billing.html
templatemail/templates/mailgun-transactional/standard_css.html
templatemail-1.1.0.dist-info/LICENSE
templatemail-1.1.0.dist-info/METADATA
templatemail-1.1.0.dist-info/WHEEL
templatemail-1.1.0.dist-info/RECORD
